{"data":{"user":{"name":"Hung Nguyen","bio":"","isHireable":false,"avatarUrl":"https://avatars.githubusercontent.com/u/76727930?u=82a5bc8702d864c8d3aa69905b1820dd4002d982&v=4","location":"Viet Nam","pinnedItems":{"totalCount":6,"edges":[{"node":{"name":"SmartDoor","description":"Smart Door System - An IOT project using face recognition to enhance house security, together with mobile application to manage","forkCount":1,"stargazers":{"totalCount":1},"url":"https://github.com/hungnguyen2611/SmartDoor","id":"R_kgDOG-7chw","diskUsage":140177,"primaryLanguage":{"name":"Kotlin","color":"#A97BFF"}}},{"node":{"name":"machine-learning-stanford","description":"exercises for course Machine Learning by Andrew Ng.","forkCount":0,"stargazers":{"totalCount":0},"url":"https://github.com/hungnguyen2611/machine-learning-stanford","id":"MDEwOlJlcG9zaXRvcnkzODEyNTgwNzc=","diskUsage":58507,"primaryLanguage":{"name":"MATLAB","color":"#e16737"}}},{"node":{"name":"MachineTranslation_with_Transformer","description":"Machine Translation Application with 5 different language data-sets","forkCount":1,"stargazers":{"totalCount":0},"url":"https://github.com/hungnguyen2611/MachineTranslation_with_Transformer","id":"R_kgDOGgs9Tw","diskUsage":21,"primaryLanguage":{"name":"Python","color":"#3572A5"}}},{"node":{"name":"GreenHouse-Micro-Climate","description":"Dynamical systems in forecasting Greenhouse Micro-climate","forkCount":0,"stargazers":{"totalCount":0},"url":"https://github.com/hungnguyen2611/GreenHouse-Micro-Climate","id":"R_kgDOGs9mdQ","diskUsage":24647,"primaryLanguage":{"name":"Python","color":"#3572A5"}}},{"node":{"name":"super-resolution","description":"Capstone Project for unsupervised real-world super resolution","forkCount":0,"stargazers":{"totalCount":2},"url":"https://github.com/hungnguyen2611/super-resolution","id":"R_kgDOIiQydw","diskUsage":144645,"primaryLanguage":{"name":"Python","color":"#3572A5"}}},{"node":{"name":"ViT-experiment","description":null,"forkCount":0,"stargazers":{"totalCount":0},"url":"https://github.com/hungnguyen2611/ViT-experiment","id":"R_kgDOIx9pSg","diskUsage":21222,"primaryLanguage":{"name":"Python","color":"#3572A5"}}}]}}}}